{"BaseModel.18963b6e-7283-418e-ad78-83f70401bbdd": {"id": "18963b6e-7283-418e-ad78-83f70401bbdd", "name": "\"test\"", "updated_at": "2024-04-27T17:54:58.304078", "__class__": "BaseModel"}, "BaseModel.e72f5c05-fb32-4e91-9681-9f6dcc2a77fa": {"id": "e72f5c05-fb32-4e91-9681-9f6dcc2a77fa", "created_at": "2024-04-27T08:12:38.597386", "updated_at": "2024-04-27T08:12:38.597446", "name": "My First Model", "my_number": 89, "__class__": "BaseModel"}, "BaseModel.773f0009-6b8e-452b-a7d2-533be3a45b40": {"id": "773f0009-6b8e-452b-a7d2-533be3a45b40", "created_at": "2024-04-27T08:14:07.436468", "updated_at": "2024-04-27T08:14:07.436715", "name": "My First Model", "my_number": 89, "__class__": "BaseModel"}, "BaseModel.a0cd97b7-bb91-4a0b-ab67-f6e6c3a2ed85": {"id": "a0cd97b7-bb91-4a0b-ab67-f6e6c3a2ed85", "created_at": "2024-04-27T08:14:18.819815", "updated_at": "2024-04-27T08:14:18.819895", "name": "My First Model", "my_number": 89, "__class__": "BaseModel"}, "BaseModel.eca9f13e-1b60-4d6d-9919-74a94437b102": {"id": "eca9f13e-1b60-4d6d-9919-74a94437b102", "created_at": "2024-04-27T08:23:34.209334", "updated_at": "2024-04-27T08:23:34.209395", "name": "My First Model", "my_number": 89, "__class__": "BaseModel"}, "User.afaeb3bf-053b-484a-8169-ace16a754ad8": {"id": "afaeb3bf-053b-484a-8169-ace16a754ad8", "created_at": "2024-04-27T18:17:10.771075", "updated_at": "2024-04-27T18:17:10.771082", "first_name": "Betty", "last_name": "Bar", "email": "airbnb@mail.com", "password": "root", "__class__": "User"}, "User.be02bff0-8366-4071-9ce4-bf1cc1195986": {"id": "be02bff0-8366-4071-9ce4-bf1cc1195986", "created_at": "2024-04-27T18:17:10.772125", "updated_at": "2024-04-27T18:17:10.772135", "first_name": "John", "email": "airbnb2@mail.com", "password": "root", "__class__": "User"}}